ksupk/__init__.py
ksupk/ksupk_mini.py
ksupk/ksupk_probability_bag.py
ksupk/ksupk_templates.py
ksupk/py.typed
ksupk/sets.py
ksupk-2026.1.25.dist-info/licenses/LICENSE
ksupk-2026.1.25.dist-info/METADATA
ksupk-2026.1.25.dist-info/WHEEL
ksupk-2026.1.25.dist-info/top_level.txt
ksupk-2026.1.25.dist-info/RECORD
