Metadata-Version: 2.4
Name: ksupk
Version: 2026.1.25
Summary: Set of mini-functions
Author-email: The220th <The220th@gmail.com>
Project-URL: Homepage, https://github.com/The220th/ksupk
Project-URL: Issues, https://github.com/The220th/ksupk/issues
Classifier: Programming Language :: Python :: 3
Classifier: License :: OSI Approved :: MIT License
Classifier: Operating System :: OS Independent
Requires-Python: >=3.7
License-File: LICENSE
Dynamic: license-file
